pygame_wrapper/UI.py
pygame_wrapper/__about__.py
pygame_wrapper/__init__.py
pygame_wrapper/colors.py
pygame_wrapper/filesystem.py
pygame_wrapper/fonts.py
pygame_wrapper/game.py
pygame_wrapper/logging.py
pygame_wrapper/menu.py
pygame_wrapper/multiplayer.py
pygame_wrapper-0.2.1.dist-info/METADATA
pygame_wrapper-0.2.1.dist-info/WHEEL
pygame_wrapper-0.2.1.dist-info/licenses/LICENSE.txt
pygame_wrapper-0.2.1.dist-info/RECORD
