Metadata-Version: 2.1
Name: pygame_wrapper
Version: 0.2.1
Summary: A simple wrapper around pygame
Project-URL: Documentation, https://github.com/Duve3/Pygame-wrapper#readme
Project-URL: Issues, https://github.com/Duve3/Pygame-wrapper/issues
Project-URL: Source, https://github.com/Duve3/Pygame-wrapper
Author-email: Duve3 <Duv3tabest@gmail.com>
License-Expression: MIT
License-File: LICENSE.txt
Keywords: pygame,wrapper
Classifier: Development Status :: 4 - Beta
Classifier: Programming Language :: Python
Classifier: Programming Language :: Python :: 3.9
Classifier: Programming Language :: Python :: 3.10
Classifier: Programming Language :: Python :: 3.11
Classifier: Programming Language :: Python :: Implementation :: CPython
Classifier: Programming Language :: Python :: Implementation :: PyPy
Requires-Python: >=3.9
Requires-Dist: pygame-ce
